lartillot_gaussian/__init__.py
lartillot_gaussian/_version.py
lartillot_gaussian/model.py
lartillot_gaussian-0.0.2.dist-info/METADATA
lartillot_gaussian-0.0.2.dist-info/WHEEL
lartillot_gaussian-0.0.2.dist-info/top_level.txt
lartillot_gaussian-0.0.2.dist-info/RECORD
