Metadata-Version: 2.1
Name: lartillot_gaussian
Version: 0.0.2
Summary: A simple multi-dimensional Gaussian model from Lartillot et al '06, useful for testing Bayesian applications.
Author-email: "avi.vajpeyi@gmail.com" <avi.vajpeyi@gmail.com>
Project-URL: Homepage, https://avivajpeyi.github.io/lartillot_gaussian/
Project-URL: Bug Reports, https://avivajpeyi.com/pywavelet/lartillot_gaussian/issues
Project-URL: Source, https://github.com/avivajpeyi/lartillot_gaussian/
Classifier: Development Status :: 3 - Alpha
Classifier: Intended Audience :: Science/Research
Classifier: License :: OSI Approved :: MIT License
Classifier: Operating System :: OS Independent
Classifier: Programming Language :: Python :: 3.8
Requires-Python: >=3.8
Requires-Dist: numpy
Requires-Dist: scipy
Provides-Extra: dev
Requires-Dist: pytest>=6.0; extra == "dev"
Requires-Dist: matplotlib; extra == "dev"
Requires-Dist: jupyter-book; extra == "dev"
